term2048/__init__.py
term2048/board.py
term2048/game.py
term2048/keypress.py
term2048/ui.py
term2048-0.2.7.dist-info/LICENSE
term2048-0.2.7.dist-info/METADATA
term2048-0.2.7.dist-info/WHEEL
term2048-0.2.7.dist-info/entry_points.txt
term2048-0.2.7.dist-info/top_level.txt
term2048-0.2.7.dist-info/RECORD
