Metadata-Version: 2.1
Name: term2048
Version: 0.2.7
Summary: 2048 in your terminal
Home-page: https://github.com/bfontaine/term2048
Author: Baptiste Fontaine
Author-email: b@ptistefontaine.fr
License: MIT
Platform: UNKNOWN
Classifier: Environment :: Console
Classifier: License :: OSI Approved :: MIT License
Classifier: Programming Language :: Python :: 2.6
Classifier: Programming Language :: Python :: 2.7
Classifier: Programming Language :: Python :: 3.2
Classifier: Programming Language :: Python :: 3.3
Classifier: Programming Language :: Python :: 3.4
Classifier: Programming Language :: Python :: 3.5
Classifier: Programming Language :: Python :: 3.6
Classifier: Programming Language :: Python :: 3.7
Requires-Dist: colorama (>=0.2.7)
Requires-Dist: argparse (>=1.1)
